openquad/__init__.py
openquad/base.py
openquad/fibonacci.py
openquad/gauss.py
openquad/geometries.py
openquad/graef.py
openquad/grid.py
openquad/karney.py
openquad/lebedev.py
openquad/monte_carlo.py
openquad/newton_cotes.py
openquad/womersley.py
openquad/data/.gitignore
openquad/data/__init__.py
openquad/data/graef/__init__.py
openquad/data/graef/git-filter-repo
openquad/data/graef/s2_design_size1002000_degree1000.npy
openquad/data/graef/s2_design_size1008_degree44.npy
openquad/data/graef/s2_design_size108_degree14.npy
openquad/data/graef/s2_design_size1104_degree46.npy
openquad/data/graef/s2_design_size1200_degree48.npy
openquad/data/graef/s2_design_size120_degree15.npy
openquad/data/graef/s2_design_size1296_degree50.npy
openquad/data/graef/s2_design_size12_degree5.npy
openquad/data/graef/s2_design_size130000_degree500.npy
openquad/data/graef/s2_design_size1404_degree52.npy
openquad/data/graef/s2_design_size144_degree16.npy
openquad/data/graef/s2_design_size1512_degree54.npy
openquad/data/graef/s2_design_size156_degree17.npy
openquad/data/graef/s2_design_size1620_degree56.npy
openquad/data/graef/s2_design_size1740_degree58.npy
openquad/data/graef/s2_design_size180_degree18.npy
openquad/data/graef/s2_design_size1860_degree60.npy
openquad/data/graef/s2_design_size192_degree19.npy
openquad/data/graef/s2_design_size1980_degree62.npy
openquad/data/graef/s2_design_size21000_degree200.npy
openquad/data/graef/s2_design_size2112_degree64.npy
openquad/data/graef/s2_design_size216_degree20.npy
openquad/data/graef/s2_design_size2244_degree66.npy
openquad/data/graef/s2_design_size234_degree21.npy
openquad/data/graef/s2_design_size2376_degree68.npy
openquad/data/graef/s2_design_size24_degree7.npy
openquad/data/graef/s2_design_size2520_degree70.npy
openquad/data/graef/s2_design_size264_degree22.npy
openquad/data/graef/s2_design_size2664_degree72.npy
openquad/data/graef/s2_design_size278_degree23.npy
openquad/data/graef/s2_design_size2808_degree74.npy
openquad-0.3.0.dist-info/METADATA
openquad-0.3.0.dist-info/WHEEL
openquad-0.3.0.dist-info/licenses/LICENSE
openquad-0.3.0.dist-info/RECORD
