Metadata-Version: 2.3
Name: openquad
Version: 0.3.0
Summary: Open database for multi-dimensional numerical integration
Author-email: Alexander Blech <alexander.blech@fu-berlin.de>
License-File: LICENSE
Keywords: Euler angles,Lebedev,SO3,illumination integral,integration,numerical integration,orientation,orientation average,quadrature,spherical quadrature
Classifier: Operating System :: OS Independent
Classifier: Programming Language :: Python :: 3
Requires-Python: >=3
Requires-Dist: numpy
Requires-Dist: quaternionic
Requires-Dist: scipy
Provides-Extra: dev
Requires-Dist: pytest; extra == 'dev'
Requires-Dist: spherical; extra == 'dev'
Provides-Extra: doc
Requires-Dist: intersphinx-registry; extra == 'doc'
Requires-Dist: numpydoc==1.7.0; extra == 'doc'
Requires-Dist: pydata-sphinx-theme==0.15.4; extra == 'doc'
Requires-Dist: sphinx-autoapi==3.2.1; extra == 'doc'
Requires-Dist: sphinx-copybutton==0.5.2; extra == 'doc'
Requires-Dist: sphinx-design==0.6.0; extra == 'doc'
Requires-Dist: sphinx==7.4.7; extra == 'doc'
Provides-Extra: examples
Requires-Dist: matplotlib; extra == 'examples'
Requires-Dist: spherical; extra == 'examples'
